celllens/__init__.py
celllens/celllens.py
celllens/datasets.py
celllens/graph.py
celllens/main.py
celllens/models.py
celllens/preprocessing.py
celllens/utils.py
celllens-0.1.1.dist-info/LICENSE
celllens-0.1.1.dist-info/METADATA
celllens-0.1.1.dist-info/WHEEL
celllens-0.1.1.dist-info/top_level.txt
celllens-0.1.1.dist-info/RECORD
